django_cachekey/__init__.py
django_cachekey-0.1.0.dev0.dist-info/METADATA
django_cachekey-0.1.0.dev0.dist-info/WHEEL
django_cachekey-0.1.0.dev0.dist-info/licenses/AUTHORS.md
django_cachekey-0.1.0.dev0.dist-info/licenses/LICENSE
django_cachekey-0.1.0.dev0.dist-info/RECORD
