Metadata-Version: 2.3
Name: django-cachekey
Version: 0.1.0.dev0
Summary: An smarter way to manage Django cache keys, inspired by Tanstack Query.
Project-URL: Documentation, https://django-cachekey.westervelt.dev/
Project-URL: Issues, https://github.com/westerveltco/django-cachekey/issues
Project-URL: Source, https://github.com/westerveltco/django-cachekey
Author-email: Josh Thomas <josh@joshthomas.dev>
License: MIT License
License-File: AUTHORS.md
License-File: LICENSE
Classifier: Development Status :: 3 - Alpha
Classifier: Framework :: Django
Classifier: Framework :: Django :: 3.2
Classifier: Framework :: Django :: 4.2
Classifier: Framework :: Django :: 5.0
Classifier: License :: OSI Approved :: MIT License
Classifier: Operating System :: OS Independent
Classifier: Programming Language :: Python
Classifier: Programming Language :: Python :: 3
Classifier: Programming Language :: Python :: 3 :: Only
Classifier: Programming Language :: Python :: 3.8
Classifier: Programming Language :: Python :: 3.9
Classifier: Programming Language :: Python :: 3.10
Classifier: Programming Language :: Python :: 3.11
Classifier: Programming Language :: Python :: 3.12
Classifier: Programming Language :: Python :: Implementation :: CPython
Requires-Python: >=3.8
Requires-Dist: django>=3.2
Provides-Extra: dev
Requires-Dist: bumpver; extra == 'dev'
Requires-Dist: copier; extra == 'dev'
Requires-Dist: copier-templates-extensions; extra == 'dev'
Requires-Dist: coverage[toml]; extra == 'dev'
Requires-Dist: django-stubs; extra == 'dev'
Requires-Dist: django-stubs-ext; extra == 'dev'
Requires-Dist: faker; extra == 'dev'
Requires-Dist: hatch; extra == 'dev'
Requires-Dist: model-bakery; extra == 'dev'
Requires-Dist: mypy; extra == 'dev'
Requires-Dist: nox[uv]; extra == 'dev'
Requires-Dist: pytest; extra == 'dev'
Requires-Dist: pytest-cov; extra == 'dev'
Requires-Dist: pytest-django; extra == 'dev'
Requires-Dist: pytest-randomly; extra == 'dev'
Requires-Dist: pytest-reverse; extra == 'dev'
Requires-Dist: pytest-xdist; extra == 'dev'
Provides-Extra: docs
Requires-Dist: cogapp; extra == 'docs'
Requires-Dist: furo; extra == 'docs'
Requires-Dist: myst-parser; extra == 'docs'
Requires-Dist: sphinx; extra == 'docs'
Requires-Dist: sphinx-autobuild; extra == 'docs'
Requires-Dist: sphinx-copybutton; extra == 'docs'
Requires-Dist: sphinx-inline-tabs; extra == 'docs'
Provides-Extra: lint
Requires-Dist: pre-commit; extra == 'lint'
